README.md
setup.cfg
setup.py
yalelaundry/__init__.py
yalelaundry/main.py
yalelaundry.egg-info/PKG-INFO
yalelaundry.egg-info/SOURCES.txt
yalelaundry.egg-info/dependency_links.txt
yalelaundry.egg-info/requires.txt
yalelaundry.egg-info/top_level.txt