Metadata-Version: 1.0
Name: yalelaundry
Version: 0.1.0
Summary: Library for fetching data from the Yale Laundry APIs.
Home-page: https://github.com/ErikBoesen/yalelaundry
Author: Erik Boesen
Author-email: me@erikboesen.com
License: GPL
Platform: UNKNOWN
